ExoViz/__init__.py
ExoViz/anim_function.py
ExoViz/exoanim.py
ExoViz/parameterquery.py
ExoViz/docs/conf.py
ExoViz-0.2.2.dist-info/METADATA
ExoViz-0.2.2.dist-info/WHEEL
ExoViz-0.2.2.dist-info/top_level.txt
ExoViz-0.2.2.dist-info/RECORD
