Metadata-Version: 2.1
Name: ExoViz
Version: 0.2.2
Requires-Dist: numpy
Requires-Dist: astropy
